{
  "index.module.js": {
    "bundled": 7078,
    "minified": 7066,
    "gzipped": 2688,
    "treeshaked": {
      "rollup": {
        "code": 14,
        "import_statements": 14
      },
      "webpack": {
        "code": 1266
      }
    }
  },
  "utils.module.js": {
    "bundled": 2997,
    "minified": 2962,
    "gzipped": 1367,
    "treeshaked": {
      "rollup": {
        "code": 28,
        "import_statements": 28
      },
      "webpack": {
        "code": 1091
      }
    }
  },
  "devtools.module.js": {
    "bundled": 1026,
    "minified": 1025,
    "gzipped": 602,
    "treeshaked": {
      "rollup": {
        "code": 28,
        "import_statements": 28
      },
      "webpack": {
        "code": 1045
      }
    }
  },
  "immer.module.js": {
    "bundled": 651,
    "minified": 632,
    "gzipped": 375,
    "treeshaked": {
      "rollup": {
        "code": 42,
        "import_statements": 42
      },
      "webpack": {
        "code": 1104
      }
    }
  },
  "optics.module.js": {
    "bundled": 625,
    "minified": 610,
    "gzipped": 381,
    "treeshaked": {
      "rollup": {
        "code": 32,
        "import_statements": 32
      },
      "webpack": {
        "code": 1061
      }
    }
  },
  "query.module.js": {
    "bundled": 1057,
    "minified": 1057,
    "gzipped": 566,
    "treeshaked": {
      "rollup": {
        "code": 57,
        "import_statements": 49
      },
      "webpack": {
        "code": 1078
      }
    }
  },
  "xstate.module.js": {
    "bundled": 1142,
    "minified": 1138,
    "gzipped": 610,
    "treeshaked": {
      "rollup": {
        "code": 29,
        "import_statements": 29
      },
      "webpack": {
        "code": 1145
      }
    }
  },
  "index.js": {
    "bundled": 9276,
    "minified": 9264,
    "gzipped": 2963
  },
  "utils.js": {
    "bundled": 3938,
    "minified": 3903,
    "gzipped": 1494
  },
  "devtools.js": {
    "bundled": 1164,
    "minified": 1163,
    "gzipped": 646
  },
  "immer.js": {
    "bundled": 962,
    "minified": 943,
    "gzipped": 454
  },
  "optics.js": {
    "bundled": 864,
    "minified": 849,
    "gzipped": 463
  },
  "query.js": {
    "bundled": 1363,
    "minified": 1363,
    "gzipped": 637
  },
  "xstate.js": {
    "bundled": 1387,
    "minified": 1383,
    "gzipped": 673
  }
}
